nullauthenticator.py
nullauthenticator-1.0.0.dist-info/DESCRIPTION.rst
nullauthenticator-1.0.0.dist-info/METADATA
nullauthenticator-1.0.0.dist-info/RECORD
nullauthenticator-1.0.0.dist-info/WHEEL
nullauthenticator-1.0.0.dist-info/metadata.json
nullauthenticator-1.0.0.dist-info/top_level.txt
